mextractor/__init__.py
mextractor/base.py
mextractor/cli.py
mextractor/constants.py
mextractor/extractors.py
mextractor/utils.py
mextractor/workflow.py
mextractor-6.0.2.dist-info/METADATA
mextractor-6.0.2.dist-info/WHEEL
mextractor-6.0.2.dist-info/entry_points.txt
mextractor-6.0.2.dist-info/RECORD
