Metadata-Version: 2.1
Name: mextractor
Version: 6.0.2
Summary: mextractor can extract media metadata to YAML and read them
Home-page: https://pypi.org/project/mextractor/
License: BSD-4
Keywords: metadata,video,image,bigdata
Author: Can H. Tartanoglu
Author-email: canhtart@gmail.com
Requires-Python: >=3.10,<3.14
Classifier: Development Status :: 4 - Beta
Classifier: License :: Other/Proprietary License
Classifier: Programming Language :: Python :: 3
Classifier: Programming Language :: Python :: 3.10
Classifier: Programming Language :: Python :: 3.11
Classifier: Programming Language :: Python :: 3.12
Classifier: Programming Language :: Python :: 3.13
Classifier: Topic :: Software Development :: Libraries :: Python Modules
Provides-Extra: video
Provides-Extra: video-extract
Requires-Dist: ffmpeg-python ; extra == "video-extract" or extra == "video"
Requires-Dist: numpy
Requires-Dist: opencv-python (>=4.6.0,<5.0.0)
Requires-Dist: pydantic (>=2.0,<3.0)
Requires-Dist: pydantic-numpy (>=7.0.0)
Requires-Dist: ruamel.yaml
Requires-Dist: typer[all] (<1)
Project-URL: Repository, https://github.com/caniko/media-metadata-extractor
